[{
  "_id": {
    "$oid": "6708ebe5fb070856d882061a"
  },
  "学籍番号": "1000001",
  "名前": "浅田 晴哉",
  "学年": 1,
  "クラス": "1組",
  "出席番号": 1
},
{
  "_id": {
    "$oid": "6708ec4efb070856d882061b"
  },
  "学籍番号": "1000002",
  "名前": "伊藤 蘭",
  "学年": 1,
  "クラス": "1組",
  "出席番号": 2
},
{
  "_id": {
    "$oid": "6708ec75fb070856d882061c"
  },
  "学籍番号": "1000003",
  "名前": "上口 麗華",
  "学年": 1,
  "クラス": "1組",
  "出席番号": 3
},
{
  "_id": {
    "$oid": "6708ec90fb070856d882061d"
  },
  "学籍番号": "1000004",
  "名前": "大塚 大将",
  "学年": 1,
  "クラス": "1組",
  "出席番号": 4
},
{
  "_id": {
    "$oid": "6708eca3fb070856d882061e"
  },
  "学籍番号": "1000005",
  "名前": "大山 粋和",
  "学年": 1,
  "クラス": "1組",
  "出席番号": 5
},
{
  "_id": {
    "$oid": "671af41ed756979302481df6"
  },
  "学籍番号": "1000006",
  "名前": "梶谷 紗弥",
  "学年": 1,
  "クラス": "1組",
  "出席番号": 6
},
{
  "_id": {
    "$oid": "671af46fd756979302481df7"
  },
  "学籍番号": "1000007",
  "名前": "川瀬 なつめ",
  "学年": 1,
  "クラス": "1組",
  "出席番号": 7
},
{
  "_id": {
    "$oid": "671af549d756979302481df9"
  },
  "学籍番号": "1000008",
  "名前": "高本 颯太",
  "学年": 1,
  "クラス": "1組",
  "出席番号": 8
},
{
  "_id": {
    "$oid": "671af576d756979302481dfa"
  },
  "学籍番号": "1000009",
  "名前": "榊原 茉菜",
  "学年": 1,
  "クラス": "1組",
  "出席番号": 9
},
{
  "_id": {
    "$oid": "671af598d756979302481dfb"
  },
  "学籍番号": "1000010",
  "名前": "佐藤 拓海",
  "学年": 1,
  "クラス": "1組",
  "出席番号": 10
},
{
  "_id": {
    "$oid": "671af665d756979302481dfc"
  },
  "学籍番号": "1000011",
  "名前": "執行 風雅",
  "学年": 1,
  "クラス": "1組",
  "出席番号": 11
},
{
  "_id": {
    "$oid": "671af6c6d756979302481dfd"
  },
  "学籍番号": "1000012",
  "名前": "柴崎 良牙",
  "学年": 1,
  "クラス": "1組",
  "出席番号": 12
},
{
  "_id": {
    "$oid": "671af6f8d756979302481dfe"
  },
  "学籍番号": "1000013",
  "名前": "鈴木 莉空",
  "学年": 1,
  "クラス": "1組",
  "出席番号": 13
},
{
  "_id": {
    "$oid": "671af71fd756979302481dff"
  },
  "学籍番号": "1000014",
  "名前": "孫 圓怡",
  "学年": 1,
  "クラス": "1組",
  "出席番号": 14
},
{
  "_id": {
    "$oid": "671af74fd756979302481e00"
  },
  "学籍番号": "1000015",
  "名前": "高橋 心愛",
  "学年": 1,
  "クラス": "1組",
  "出席番号": 15
},
{
  "_id": {
    "$oid": "671af789d756979302481e01"
  },
  "学籍番号": "1000016",
  "名前": "高田 智一",
  "学年": 1,
  "クラス": "1組",
  "出席番号": 16
},
{
  "_id": {
    "$oid": "671af7fed756979302481e02"
  },
  "学籍番号": "1000017",
  "名前": "武田 沙優",
  "学年": 1,
  "クラス": "1組",
  "出席番号": 17
},
{
  "_id": {
    "$oid": "671af83ed756979302481e04"
  },
  "学籍番号": "1000018",
  "名前": "武村 りこ",
  "学年": 1,
  "クラス": "1組",
  "出席番号": 18
},
{
  "_id": {
    "$oid": "671af85fd756979302481e05"
  },
  "学籍番号": "1000019",
  "名前": "出口 唯斗",
  "学年": 1,
  "クラス": "1組",
  "出席番号": 19
},
{
  "_id": {
    "$oid": "671af8a1d756979302481e06"
  },
  "学籍番号": "1000020",
  "名前": "冨岡 翔",
  "学年": 1,
  "クラス": "1組",
  "出席番号": 20
},
{
  "_id": {
    "$oid": "671af8ced756979302481e07"
  },
  "学籍番号": "1000021",
  "名前": "中村 拓夢",
  "学年": 1,
  "クラス": "1組",
  "出席番号": 21
},
{
  "_id": {
    "$oid": "671af8e3d756979302481e08"
  },
  "学籍番号": "1000022",
  "名前": "服部 耀大",
  "学年": 1,
  "クラス": "1組",
  "出席番号": 22
},
{
  "_id": {
    "$oid": "671af8fbd756979302481e09"
  },
  "学籍番号": "1000023",
  "名前": "藤原 希来莉",
  "学年": 1,
  "クラス": "1組",
  "出席番号": 23
},
{
  "_id": {
    "$oid": "671af913d756979302481e0a"
  },
  "学籍番号": "1000024",
  "名前": "水谷 八子",
  "学年": 1,
  "クラス": "1組",
  "出席番号": 24
},
{
  "_id": {
    "$oid": "671af947d756979302481e0b"
  },
  "学籍番号": "1000025",
  "名前": "八木 雅人",
  "学年": 1,
  "クラス": "1組",
  "出席番号": 25
},
{
  "_id": {
    "$oid": "671af962d756979302481e0c"
  },
  "学籍番号": "1000026",
  "名前": "安永 弘",
  "学年": 1,
  "クラス": "1組",
  "出席番号": 26
},
{
  "_id": {
    "$oid": "671af984d756979302481e0d"
  },
  "学籍番号": "1000027",
  "名前": "山崎 怜奈",
  "学年": 1,
  "クラス": "1組",
  "出席番号": 27
},
{
  "_id": {
    "$oid": "671af9aed756979302481e0e"
  },
  "学籍番号": "1000028",
  "名前": "山澄 綾子",
  "学年": 1,
  "クラス": "1組",
  "出席番号": 28
},
{
  "_id": {
    "$oid": "671af9c3d756979302481e0f"
  },
  "学籍番号": "1000029",
  "名前": "吉田 眞実",
  "学年": 1,
  "クラス": "1組",
  "出席番号": 29
},
{
  "_id": {
    "$oid": "671af9dfd756979302481e10"
  },
  "学籍番号": "1000030",
  "名前": "蓬田 結子",
  "学年": 1,
  "クラス": "1組",
  "出席番号": 30
},
{
  "_id": {
    "$oid": "671af9ffd756979302481e11"
  },
  "学籍番号": "1000031",
  "名前": "度会 喜久子",
  "学年": 1,
  "クラス": "1組",
  "出席番号": 31
},
{
  "_id": {
    "$oid": "671afa25d756979302481e12"
  },
  "学籍番号": "1000032",
  "名前": "足立 千夏",
  "学年": 1,
  "クラス": "2組",
  "出席番号": 1
},
{
  "_id": {
    "$oid": "671afa8dd756979302481e13"
  },
  "学籍番号": "1000033",
  "名前": "伊藤 輝愛来",
  "学年": 1,
  "クラス": "2組",
  "出席番号": 2
},
{
  "_id": {
    "$oid": "671afafad756979302481e14"
  },
  "学籍番号": "1000034",
  "名前": "江部 典馬",
  "学年": 1,
  "クラス": "2組",
  "出席番号": 3
},
{
  "_id": {
    "$oid": "671afb2ed756979302481e15"
  },
  "学籍番号": "1000035",
  "名前": "大橋 鈴菜",
  "学年": 1,
  "クラス": "2組",
  "出席番号": 4
},
{
  "_id": {
    "$oid": "671afb4fd756979302481e16"
  },
  "学籍番号": "1000036",
  "名前": "ｵﾀﾞ ｱﾙﾂﾙ ﾅｶﾀ",
  "学年": 1,
  "クラス": "2組",
  "出席番号": 5
},
{
  "_id": {
    "$oid": "671afb86d756979302481e18"
  },
  "学籍番号": "1000037",
  "名前": "片野 秀斗",
  "学年": 1,
  "クラス": "2組",
  "出席番号": 6
},
{
  "_id": {
    "$oid": "671afbc4d756979302481e19"
  },
  "学籍番号": "1000038",
  "名前": "久遠寺 航成",
  "学年": 1,
  "クラス": "2組",
  "出席番号": 7
},
{
  "_id": {
    "$oid": "671afbe8d756979302481e1a"
  },
  "学籍番号": "1000039",
  "名前": "小宮 あいり",
  "学年": 1,
  "クラス": "2組",
  "出席番号": 8
},
{
  "_id": {
    "$oid": "67369e7df830bdc22347d1eb"
  },
  "学籍番号": "1000040",
  "名前": "坂元 祐都",
  "学年": 1,
  "クラス": "2組",
  "出席番号": 9
},
{
  "_id": {
    "$oid": "67369efdf830bdc22347d1ec"
  },
  "学籍番号": "1000041",
  "名前": "佐藤 丈一郎",
  "学年": 1,
  "クラス": "2組",
  "出席番号": 10
},
{
  "_id": {
    "$oid": "67369f33f830bdc22347d1ed"
  },
  "学籍番号": "1000042",
  "名前": "執行 和年",
  "学年": 1,
  "クラス": "2組",
  "出席番号": 11
},
{
  "_id": {
    "$oid": "67369f55f830bdc22347d1ee"
  },
  "学籍番号": "1000043",
  "名前": "清水 玲雄",
  "学年": 1,
  "クラス": "2組",
  "出席番号": 12
},
{
  "_id": {
    "$oid": "67369f87f830bdc22347d1ef"
  },
  "学籍番号": "1000044",
  "名前": "鈴木 隼人",
  "学年": 1,
  "クラス": "2組",
  "出席番号": 13
},
{
  "_id": {
    "$oid": "67369fa2f830bdc22347d1f0"
  },
  "学籍番号": "1000045",
  "名前": "高月 美紅",
  "学年": 1,
  "クラス": "2組",
  "出席番号": 14
},
{
  "_id": {
    "$oid": "67369fbcf830bdc22347d1f1"
  },
  "学籍番号": "1000046",
  "名前": "高橋 妃果莉",
  "学年": 1,
  "クラス": "2組",
  "出席番号": 15
},
{
  "_id": {
    "$oid": "67369fccf830bdc22347d1f2"
  },
  "学籍番号": "1000047",
  "名前": "武田 汐里",
  "学年": 1,
  "クラス": "2組",
  "出席番号": 16
},
{
  "_id": {
    "$oid": "67369fe1f830bdc22347d1f3"
  },
  "学籍番号": "1000048",
  "名前": "田丸 姫星",
  "学年": 1,
  "クラス": "2組",
  "出席番号": 17
},
{
  "_id": {
    "$oid": "67369ff0f830bdc22347d1f4"
  },
  "学籍番号": "1000049",
  "名前": "中田 響",
  "学年": 1,
  "クラス": "2組",
  "出席番号": 18
},
{
  "_id": {
    "$oid": "6736a000f830bdc22347d1f5"
  },
  "学籍番号": "1000050",
  "名前": "中村 峻生",
  "学年": 1,
  "クラス": "2組",
  "出席番号": 19
},
{
  "_id": {
    "$oid": "6736a00ef830bdc22347d1f6"
  },
  "学籍番号": "1000051",
  "名前": "東口 直雄",
  "学年": 1,
  "クラス": "2組",
  "出席番号": 20
},
{
  "_id": {
    "$oid": "6736a027f830bdc22347d1f7"
  },
  "学籍番号": "1000052",
  "名前": "福島 まり",
  "学年": 1,
  "クラス": "2組",
  "出席番号": 21
},
{
  "_id": {
    "$oid": "6736a038f830bdc22347d1f8"
  },
  "学籍番号": "1000053",
  "名前": "藤原 隆甫",
  "学年": 1,
  "クラス": "2組",
  "出席番号": 22
},
{
  "_id": {
    "$oid": "6736a049f830bdc22347d1f9"
  },
  "学籍番号": "1000054",
  "名前": "水谷 茉優",
  "学年": 1,
  "クラス": "2組",
  "出席番号": 23
},
{
  "_id": {
    "$oid": "6736a061f830bdc22347d1fa"
  },
  "学籍番号": "1000055",
  "名前": "薮崎 優衣",
  "学年": 1,
  "クラス": "2組",
  "出席番号": 24
},
{
  "_id": {
    "$oid": "6736a071f830bdc22347d1fb"
  },
  "学籍番号": "1000056",
  "名前": "山下 真綿",
  "学年": 1,
  "クラス": "2組",
  "出席番号": 25
},
{
  "_id": {
    "$oid": "6736a083f830bdc22347d1fc"
  },
  "学籍番号": "1000057",
  "名前": "山本 裕人",
  "学年": 1,
  "クラス": "2組",
  "出席番号": 26
},
{
  "_id": {
    "$oid": "6736a406f830bdc22347d1fd"
  },
  "学籍番号": "1000058",
  "名前": "吉田 修介",
  "学年": 1,
  "クラス": "2組",
  "出席番号": 27
},
{
  "_id": {
    "$oid": "6736a417f830bdc22347d1fe"
  },
  "学籍番号": "1000059",
  "名前": "我妻 遥",
  "学年": 1,
  "クラス": "2組",
  "出席番号": 28
},
{
  "_id": {
    "$oid": "6736a42df830bdc22347d1ff"
  },
  "学籍番号": "1000060",
  "名前": "井口 和歌",
  "学年": 1,
  "クラス": "3組",
  "出席番号": 1
},
{
  "_id": {
    "$oid": "6736a43df830bdc22347d200"
  },
  "学籍番号": "1000061",
  "名前": "岩田 舞",
  "学年": 1,
  "クラス": "3組",
  "出席番号": 2
},
{
  "_id": {
    "$oid": "6736a44ef830bdc22347d201"
  },
  "学籍番号": "1000062",
  "名前": "大内 理人",
  "学年": 1,
  "クラス": "3組",
  "出席番号": 3
},
{
  "_id": {
    "$oid": "6736a466f830bdc22347d202"
  },
  "学籍番号": "1000063",
  "名前": "大清水 亜美",
  "学年": 1,
  "クラス": "3組",
  "出席番号": 4
},
{
  "_id": {
    "$oid": "6736a474f830bdc22347d203"
  },
  "学籍番号": "1000064",
  "名前": "大村 瑞貴",
  "学年": 1,
  "クラス": "3組",
  "出席番号": 5
},
{
  "_id": {
    "$oid": "6736a483f830bdc22347d204"
  },
  "学籍番号": "1000065",
  "名前": "小幡 魁人",
  "学年": 1,
  "クラス": "3組",
  "出席番号": 6
},
{
  "_id": {
    "$oid": "6736a494f830bdc22347d205"
  },
  "学籍番号": "1000066",
  "名前": "上岸 志保",
  "学年": 1,
  "クラス": "3組",
  "出席番号": 7
},
{
  "_id": {
    "$oid": "6736a4a6f830bdc22347d206"
  },
  "学籍番号": "1000067",
  "名前": "川尻 駿貴",
  "学年": 1,
  "クラス": "3組",
  "出席番号": 8
},
{
  "_id": {
    "$oid": "6736a4b7f830bdc22347d207"
  },
  "学籍番号": "1000068",
  "名前": "久保 勇太郎",
  "学年": 1,
  "クラス": "3組",
  "出席番号": 9
},
{
  "_id": {
    "$oid": "6736a4c7f830bdc22347d208"
  },
  "学籍番号": "1000069",
  "名前": "近藤 光",
  "学年": 1,
  "クラス": "3組",
  "出席番号": 10
},
{
  "_id": {
    "$oid": "6736a4d5f830bdc22347d209"
  },
  "学籍番号": "1000070",
  "名前": "佐津川 七海",
  "学年": 1,
  "クラス": "3組",
  "出席番号": 11
},
{
  "_id": {
    "$oid": "6736a4e3f830bdc22347d20a"
  },
  "学籍番号": "1000071",
  "名前": "沢田 圭一",
  "学年": 1,
  "クラス": "3組",
  "出席番号": 12
},
{
  "_id": {
    "$oid": "6736a4fdf830bdc22347d20b"
  },
  "学籍番号": "1000072",
  "名前": "柴崎 愛",
  "学年": 1,
  "クラス": "3組",
  "出席番号": 13
},
{
  "_id": {
    "$oid": "6736a519f830bdc22347d20c"
  },
  "学籍番号": "1000073",
  "名前": "菅沼 太陽",
  "学年": 1,
  "クラス": "3組",
  "出席番号": 14
},
{
  "_id": {
    "$oid": "6736a528f830bdc22347d20d"
  },
  "学籍番号": "1000074",
  "名前": "瀬戸 昊大",
  "学年": 1,
  "クラス": "3組",
  "出席番号": 15
},
{
  "_id": {
    "$oid": "6736a536f830bdc22347d20e"
  },
  "学籍番号": "1000075",
  "名前": "髙橋 成都",
  "学年": 1,
  "クラス": "3組",
  "出席番号": 16
},
{
  "_id": {
    "$oid": "6736a546f830bdc22347d20f"
  },
  "学籍番号": "1000076",
  "名前": "竹尾 源希",
  "学年": 1,
  "クラス": "3組",
  "出席番号": 17
},
{
  "_id": {
    "$oid": "6736a553f830bdc22347d210"
  },
  "学籍番号": "1000077",
  "名前": "竹之内 ひかり",
  "学年": 1,
  "クラス": "3組",
  "出席番号": 18
},
{
  "_id": {
    "$oid": "6736a562f830bdc22347d211"
  },
  "学籍番号": "1000078",
  "名前": "辻 優花",
  "学年": 1,
  "クラス": "3組",
  "出席番号": 19
},
{
  "_id": {
    "$oid": "6736a575f830bdc22347d212"
  },
  "学籍番号": "1000079",
  "名前": "永田 唯",
  "学年": 1,
  "クラス": "3組",
  "出席番号": 20
},
{
  "_id": {
    "$oid": "6736a585f830bdc22347d213"
  },
  "学籍番号": "1000080",
  "名前": "西出 壮真",
  "学年": 1,
  "クラス": "3組",
  "出席番号": 21
},
{
  "_id": {
    "$oid": "6736a594f830bdc22347d214"
  },
  "学籍番号": "1000081",
  "名前": "日暮 凛太朗",
  "学年": 1,
  "クラス": "3組",
  "出席番号": 22
},
{
  "_id": {
    "$oid": "6736a5a8f830bdc22347d215"
  },
  "学籍番号": "1000082",
  "名前": "平野 伶大",
  "学年": 1,
  "クラス": "3組",
  "出席番号": 23
},
{
  "_id": {
    "$oid": "6736a5b8f830bdc22347d216"
  },
  "学籍番号": "1000083",
  "名前": "藤川 未久",
  "学年": 1,
  "クラス": "3組",
  "出席番号": 24
},
{
  "_id": {
    "$oid": "6736a5c6f830bdc22347d217"
  },
  "学籍番号": "1000084",
  "名前": "松岡 胡実",
  "学年": 1,
  "クラス": "3組",
  "出席番号": 25
},
{
  "_id": {
    "$oid": "6736a5d9f830bdc22347d218"
  },
  "学籍番号": "1000085",
  "名前": "宮良 咲希",
  "学年": 1,
  "クラス": "3組",
  "出席番号": 26
},
{
  "_id": {
    "$oid": "6736a5e7f830bdc22347d219"
  },
  "学籍番号": "1000086",
  "名前": "山崎 蓮",
  "学年": 1,
  "クラス": "3組",
  "出席番号": 27
},
{
  "_id": {
    "$oid": "6736a5f6f830bdc22347d21a"
  },
  "学籍番号": "1000087",
  "名前": "山下 愛莉",
  "学年": 1,
  "クラス": "3組",
  "出席番号": 28
},
{
  "_id": {
    "$oid": "6736a605f830bdc22347d21b"
  },
  "学籍番号": "1000088",
  "名前": "米村 航志",
  "学年": 1,
  "クラス": "3組",
  "出席番号": 29
},
{
  "_id": {
    "$oid": "6736a617f830bdc22347d21c"
  },
  "学籍番号": "1000089",
  "名前": "渡邉 はずみ",
  "学年": 1,
  "クラス": "3組",
  "出席番号": 30
}]